ass_whispers/__init__.py
ass_whispers/__main__.py
ass_whispers-0.2.0.dist-info/entry_points.txt
ass_whispers-0.2.0.dist-info/LICENSE
ass_whispers-0.2.0.dist-info/METADATA
ass_whispers-0.2.0.dist-info/WHEEL
ass_whispers-0.2.0.dist-info/RECORD
