Metadata-Version: 2.3
Name: ass-whispers
Version: 0.2.0
Summary: Transcribe audio to text for Aegisub macro Whispers
License: BSD 3-Clause License
Keywords: subtitles,transcription,aegisub,whisper,automation
Author: Ghegghe
Author-email: nicopante98@gmail.com
Requires-Python: >=3.9
Classifier: Development Status :: 4 - Beta
Classifier: Intended Audience :: Developers
Classifier: Topic :: Multimedia :: Sound/Audio :: Speech
Classifier: License :: OSI Approved :: MIT License
Classifier: Programming Language :: Python :: 3
Classifier: Programming Language :: Python :: 3.9
Classifier: Programming Language :: Python :: 3.10
Classifier: Programming Language :: Python :: 3.11
Classifier: Programming Language :: Python :: 3.12
Classifier: Operating System :: OS Independent
Requires-Dist: faster-whisper (>=1.1.1,<2.0.0)
Project-URL: Repository, https://github.com/Ghegghe/aegis-lua-scripts
